ChildProject/__init__.py
ChildProject/annotations.py
ChildProject/cmdline.py
ChildProject/converters.py
ChildProject/metrics.py
ChildProject/projects.py
ChildProject/tables.py
ChildProject/utils.py
ChildProject/pipelines/__init__.py
ChildProject/pipelines/anonymize.py
ChildProject/pipelines/conversationFunctions.py
ChildProject/pipelines/conversations.py
ChildProject/pipelines/derivations.py
ChildProject/pipelines/eafbuilder.py
ChildProject/pipelines/fake_panoptes.py
ChildProject/pipelines/metrics.py
ChildProject/pipelines/metricsFunctions.py
ChildProject/pipelines/pipeline.py
ChildProject/pipelines/processors.py
ChildProject/pipelines/samplers.py
ChildProject/pipelines/zooniverse.py
ChildProject/templates/__init__.py
ChildProject/templates/basic.etf
ChildProject/templates/basic.pfsx
ChildProject/templates/native.etf
ChildProject/templates/native.pfsx
ChildProject/templates/non-native.etf
ChildProject/templates/non-native.pfsx
childproject-0.4.5.dist-info/licenses/LICENSE
childproject-0.4.5.dist-info/METADATA
childproject-0.4.5.dist-info/WHEEL
childproject-0.4.5.dist-info/entry_points.txt
childproject-0.4.5.dist-info/top_level.txt
childproject-0.4.5.dist-info/RECORD
