Metadata-Version: 2.4
Name: ChildProject
Version: 0.4.5
Summary: LAAC@LSCP
Author-email: Lucas Gautheron <lucas.gautheron@gmail.com>, Loann Peurey <loannpeurey@gmail.com>
License: MIT License
Project-URL: Homepage, https://github.com/LAAC-LSCP/ChildProject
Project-URL: Documentation, https://childproject.readthedocs.io/en/latest/
Classifier: Development Status :: 3 - Alpha
Classifier: Intended Audience :: Science/Research
Classifier: License :: OSI Approved :: MIT License
Classifier: Natural Language :: English
Classifier: Operating System :: Unix
Classifier: Programming Language :: Python
Classifier: Topic :: Scientific/Engineering
Requires-Python: >=3.8
License-File: LICENSE
Requires-Dist: colorlog
Requires-Dist: GitPython
Requires-Dist: librosa>=0.11.0
Requires-Dist: lxml
Requires-Dist: matplotlib
Requires-Dist: nltk
Requires-Dist: numpy>=1.17
Requires-Dist: pandas<=3.0.0,>=2.0.0
Requires-Dist: panoptes_client
Requires-Dist: praat-parselmouth
Requires-Dist: pyannote.core
Requires-Dist: pydub
Requires-Dist: pylangacq
Requires-Dist: pympi-ling
Requires-Dist: python-dateutil>=2.8.1
Requires-Dist: PyYAML
Requires-Dist: requests>=2.25.0
Requires-Dist: soundfile
Provides-Extra: tests
Requires-Dist: pytest; extra == "tests"
Provides-Extra: docs
Requires-Dist: sphinx>=6.2.1; extra == "docs"
Requires-Dist: sphinx_rtd_theme; extra == "docs"
Requires-Dist: sphinx-tabs; extra == "docs"
Requires-Dist: datalad; extra == "docs"
Provides-Extra: repository
Requires-Dist: datalad; extra == "repository"
Dynamic: license-file
